dsroot/__init__.py
dsroot/singleton.py
dsroot/time.py
dsroot-0.0.3.dist-info/LICENSE
dsroot-0.0.3.dist-info/METADATA
dsroot-0.0.3.dist-info/WHEEL
dsroot-0.0.3.dist-info/RECORD
