Metadata-Version: 2.3
Name: dsroot
Version: 0.0.3
Summary: Core dependencies for DS packages
License: MIT
Keywords: singleton,utilities,core
Author: Danny Stewart
Author-email: danny@stewart.cc
Requires-Python: >=3.12
Classifier: Intended Audience :: Developers
Classifier: License :: OSI Approved :: MIT License
Classifier: Programming Language :: Python :: 3
Classifier: Programming Language :: Python :: 3.12
Requires-Dist: tzlocal (>=5.3.1,<6.0.0)
